odoo/addons/l10n_es_ticketbai_batuz/README.rst
odoo/addons/l10n_es_ticketbai_batuz/__init__.py
odoo/addons/l10n_es_ticketbai_batuz/__manifest__.py
odoo/addons/l10n_es_ticketbai_batuz/hooks.py
odoo/addons/l10n_es_ticketbai_batuz/data/account_fiscal_position_template_data.xml
odoo/addons/l10n_es_ticketbai_batuz/data/queue_job_data.xml
odoo/addons/l10n_es_ticketbai_batuz/data/tbai_tax_map_data.xml
odoo/addons/l10n_es_ticketbai_batuz/data/tbai_vat_regime_key_data.xml
odoo/addons/l10n_es_ticketbai_batuz/i18n/es.po
odoo/addons/l10n_es_ticketbai_batuz/i18n/eu.po
odoo/addons/l10n_es_ticketbai_batuz/i18n/l10n_es_ticketbai_batuz.pot
odoo/addons/l10n_es_ticketbai_batuz/models/__init__.py
odoo/addons/l10n_es_ticketbai_batuz/models/account_fiscal_position.py
odoo/addons/l10n_es_ticketbai_batuz/models/account_move.py
odoo/addons/l10n_es_ticketbai_batuz/models/chart_template.py
odoo/addons/l10n_es_ticketbai_batuz/models/lroe_operation.py
odoo/addons/l10n_es_ticketbai_batuz/models/res_company.py
odoo/addons/l10n_es_ticketbai_batuz/models/res_partner.py
odoo/addons/l10n_es_ticketbai_batuz/models/ticketbai_invoice.py
odoo/addons/l10n_es_ticketbai_batuz/models/ticketbai_vat_regime_key.py
odoo/addons/l10n_es_ticketbai_batuz/readme/CONTRIBUTORS.rst
odoo/addons/l10n_es_ticketbai_batuz/readme/DESCRIPTION.rst
odoo/addons/l10n_es_ticketbai_batuz/readme/INSTALL.rst
odoo/addons/l10n_es_ticketbai_batuz/readme/USAGE.rst
odoo/addons/l10n_es_ticketbai_batuz/security/ir_rule.xml
odoo/addons/l10n_es_ticketbai_batuz/static/description/icon.png
odoo/addons/l10n_es_ticketbai_batuz/static/description/index.html
odoo/addons/l10n_es_ticketbai_batuz/static/src/description/icon.png
odoo/addons/l10n_es_ticketbai_batuz/static/src/img/binovo_logo.jpg
odoo/addons/l10n_es_ticketbai_batuz/static/src/img/binovo_logo_peque.jpg
odoo/addons/l10n_es_ticketbai_batuz/views/account_fiscal_position_views.xml
odoo/addons/l10n_es_ticketbai_batuz/views/account_journal_views.xml
odoo14_addon_l10n_es_ticketbai_batuz-14.0.1.2.3.dist-info/METADATA
odoo14_addon_l10n_es_ticketbai_batuz-14.0.1.2.3.dist-info/WHEEL
odoo14_addon_l10n_es_ticketbai_batuz-14.0.1.2.3.dist-info/top_level.txt
odoo14_addon_l10n_es_ticketbai_batuz-14.0.1.2.3.dist-info/RECORD
