Metadata-Version: 2.1
Name: odoo14-addon-l10n-es-ticketbai-batuz
Version: 14.0.1.2.3
Summary: TicketBAI - Batuz - declaración de todas las operaciones de venta realizadas por las personas y entidades que desarrollan actividades económicas en Bizkaia
Home-page: https://github.com/OCA/l10n-spain
Author: Binovo,Digital5,Odoo Community Association (OCA)
Author-email: support@odoo-community.org
License: AGPL-3
Platform: UNKNOWN
Classifier: Programming Language :: Python
Classifier: Framework :: Odoo
Classifier: Framework :: Odoo :: 14.0
Classifier: License :: OSI Approved :: GNU Affero General Public License v3
Classifier: Development Status :: 3 - Alpha
Requires-Python: >=3.6
Requires-Dist: odoo14-addon-l10n-es-ticketbai
Requires-Dist: odoo14-addon-l10n-es-ticketbai-api-batuz
Requires-Dist: odoo14-addon-queue-job
Requires-Dist: odoo <14.1dev,>=14.0a
